numina/conftest.py
numina/_version.py
numina/constants.py
numina/datamodel.py
numina/__init__.py
numina/logger.py
numina/treedict.py
numina/keydef.py
numina/exceptions.py
numina/tools/resample_wave_3d_cube.py
numina/tools/stack_hdus.py
numina/tools/generate_mosaic_of_2d_images.py
numina/tools/r6_addnf.py
numina/tools/include_adrtheor_in_3d_cube.py
numina/tools/sp3d_with_ds9.py
numina/tools/imath3d.py
numina/tools/pixel_to_world.py
numina/tools/genimage.py
numina/tools/arg_file_is_new.py
numina/tools/ctext.py
numina/tools/imath.py
numina/tools/pixel_solid_angle_arcsec2.py
numina/tools/__init__.py
numina/tools/find_optimal_celestial_wcs_with_adr.py
numina/tools/extract_2d_slice_from_3d_cube.py
numina/tools/generate_mosaic_of_3d_cubes.py
numina/tools/adr_correction_from_extension_in_3d_cube.py
numina/tools/subsets_of_fileinfo_from_txt.py
numina/tools/r6_replace_image.py
numina/tools/world_to_pixel.py
numina/tools/r6_imcombine.py
numina/tools/r6_delete_extension.py
numina/tools/measure_slice_xy_offsets_in_3d_cube.py
numina/tools/compute_adr_wavelength.py
numina/tools/compare_adr_extensions_in_3d_cube.py
numina/tools/r6_insert_keyword.py
numina/tools/check_setstate_getstate.py
numina/tools/add_script_info_to_fits_history.py
numina/tools/tests/__init__.py
numina/tools/tests/test_imath.py
numina/types/typedialect.py
numina/types/qc.py
numina/types/linescatalog.py
numina/types/dataframe.py
numina/types/__init__.py
numina/types/multitype.py
numina/types/frame.py
numina/types/structured.py
numina/types/product.py
numina/types/datatype.py
numina/types/array.py
numina/types/base.py
numina/types/obsresult.py
numina/types/tests/test_multitype.py
numina/types/tests/test_dataframetype.py
numina/types/tests/__init__.py
numina/types/tests/test_datatype.py
numina/types/tests/test_listtype.py
numina/types/tests/test_types.py
numina/core/validator.py
numina/core/dataholders.py
numina/core/config.py
numina/core/tagexpr.py
numina-0.36.0.dist-info/RECORD
numina-0.36.0.dist-info/WHEEL
numina-0.36.0.dist-info/entry_points.txt
numina-0.36.0.dist-info/top_level.txt
numina-0.36.0.dist-info/METADATA
numina-0.36.0.dist-info/licenses/AUTHORS.rst
numina-0.36.0.dist-info/licenses/LICENSE.txt
