Metadata-Version: 2.4
Name: numina
Version: 0.36.0
Summary: Astronomy data reduction library
Author-email: Sergio Pascual <sergiopr@fis.ucm.es>
License: GPL-3.0-or-later
Project-URL: Homepage, https://github.com/guaix-ucm/numina
Project-URL: Repository, https://github.com/guaix-ucm/numina.git
Project-URL: Documentation, https://numina.readthedocs.io/en/stable/
Classifier: Programming Language :: C
Classifier: Programming Language :: C++
Classifier: Programming Language :: Cython
Classifier: Programming Language :: Python :: 3.10
Classifier: Programming Language :: Python :: 3.11
Classifier: Programming Language :: Python :: 3.12
Classifier: Programming Language :: Python :: 3.13
Classifier: Programming Language :: Python :: 3.14
Classifier: Programming Language :: Python :: Implementation :: CPython
Classifier: Development Status :: 3 - Alpha
Classifier: Environment :: Console
Classifier: Intended Audience :: Science/Research
Classifier: License :: OSI Approved :: GNU General Public License (GPL)
Classifier: Operating System :: OS Independent
Classifier: Topic :: Scientific/Engineering :: Astronomy
Classifier: Topic :: Software Development :: Libraries :: Application Frameworks
Requires-Python: >=3.10
License-File: LICENSE.txt
License-File: AUTHORS.rst
Requires-Dist: astropy>=6.1.7
Requires-Dist: attrs
Requires-Dist: backports.entry_points_selectable
Requires-Dist: ccdproc
Requires-Dist: importlib_resources
Requires-Dist: lmfit
Requires-Dist: matplotlib
Requires-Dist: numpy>=2
Requires-Dist: python-dateutil>=2.7.0
Requires-Dist: PyYaml
Requires-Dist: reproject
Requires-Dist: rich
Requires-Dist: scikit-image
Requires-Dist: scipy
Requires-Dist: spherical-geometry
Requires-Dist: teareduce
Requires-Dist: typing-extensions
Provides-Extra: test
Requires-Dist: pytest>=6; extra == "test"
Requires-Dist: pytest-remotedata; extra == "test"
Provides-Extra: docs
Requires-Dist: sphinx<7.0.0; extra == "docs"
Requires-Dist: sphinx_rtd_theme; extra == "docs"
Dynamic: license-file
